[
  {
    "company": "Alpha Medical",
    "clientMatterNumber": "CM1001",
    "contactFirstName": "John",
    "contactLastName": "Smith",
    "dlaFirstName": "David",
    "dlaLastName": "Adams",
    "dlaContactIdentity": "DLA001"
  },
  {
    "company": "Alpha Medica",
    "clientMatterNumber": "CM1002",
    "contactFirstName": "Jonathan",
    "contactLastName": "Smith",
    "dlaFirstName": "David",
    "dlaLastName": "Adams",
    "dlaContactIdentity": "DLA002"
  },
  {
    "company": "Beta Solutions",
    "clientMatterNumber": "CM1003",
    "contactFirstName": "Mary",
    "contactLastName": "Johnson",
    "dlaFirstName": "Sara",
    "dlaLastName": "White",
    "dlaContactIdentity": "DLA003"
  },
  {
    "company": "Beta Solution Group",
    "clientMatterNumber": "CM1004",
    "contactFirstName": "Marie",
    "contactLastName": "Johnston",
    "dlaFirstName": "Sara",
    "dlaLastName": "White",
    "dlaContactIdentity": "DLA004"
  },
  {
    "company": "Gamma Tech",
    "clientMatterNumber": "CM1005",
    "contactFirstName": "James",
    "contactLastName": "Brown",
    "dlaFirstName": "Alan",
    "dlaLastName": "Green",
    "dlaContactIdentity": "DLA005"
  },
  {
    "company": "Gamma Technologies",
    "clientMatterNumber": "CM1006",
    "contactFirstName": "Jim",
    "contactLastName": "Brown",
    "dlaFirstName": "Alan",
    "dlaLastName": "Green",
    "dlaContactIdentity": "DLA006"
  },
  {
    "company": "Delta Corp",
    "clientMatterNumber": "CM1007",
    "contactFirstName": "Linda",
    "contactLastName": "Taylor",
    "dlaFirstName": "Robert",
    "dlaLastName": "King",
    "dlaContactIdentity": "DLA007"
  },
  {
    "company": "Delta Corporation",
    "clientMatterNumber": "CM1008",
    "contactFirstName": "Lynda",
    "contactLastName": "Taylor",
    "dlaFirstName": "Robert",
    "dlaLastName": "King",
    "dlaContactIdentity": "DLA008"
  },
  {
    "company": "Epsilon LLC",
    "clientMatterNumber": "CM1009",
    "contactFirstName": "Michael",
    "contactLastName": "Davis",
    "dlaFirstName": "Chris",
    "dlaLastName": "Reed",
    "dlaContactIdentity": "DLA009"
  },
  {
    "company": "Epsilon Group",
    "clientMatterNumber": "CM1010",
    "contactFirstName": "Mike",
    "contactLastName": "Davies",
    "dlaFirstName": "Chris",
    "dlaLastName": "Reed",
    "dlaContactIdentity": "DLA010"
  },
  {
    "company": "Zeta Health",
    "clientMatterNumber": "CM1011",
    "contactFirstName": "Barbara",
    "contactLastName": "Wilson",
    "dlaFirstName": "Emma",
    "dlaLastName": "Scott",
    "dlaContactIdentity": "DLA011"
  },
  {
    "company": "Zeta Healthcare",
    "clientMatterNumber": "CM1012",
    "contactFirstName": "Barb",
    "contactLastName": "Wilson",
    "dlaFirstName": "Emma",
    "dlaLastName": "Scott",
    "dlaContactIdentity": "DLA012"
  },
  {
    "company": "Omega Partners",
    "clientMatterNumber": "CM1013",
    "contactFirstName": "William",
    "contactLastName": "Miller",
    "dlaFirstName": "Sophia",
    "dlaLastName": "Hall",
    "dlaContactIdentity": "DLA013"
  },
  {
    "company": "Omega Partner Services",
    "clientMatterNumber": "CM1014",
    "contactFirstName": "Will",
    "contactLastName": "Miller",
    "dlaFirstName": "Sophia",
    "dlaLastName": "Hall",
    "dlaContactIdentity": "DLA014"
  },
  {
    "company": "Prime Consulting",
    "clientMatterNumber": "CM1015",
    "contactFirstName": "Elizabeth",
    "contactLastName": "Moore",
    "dlaFirstName": "Daniel",
    "dlaLastName": "Young",
    "dlaContactIdentity": "DLA015"
  },
  {
    "company": "Prime Consult",
    "clientMatterNumber": "CM1016",
    "contactFirstName": "Liz",
    "contactLastName": "Moore",
    "dlaFirstName": "Daniel",
    "dlaLastName": "Young",
    "dlaContactIdentity": "DLA016"
  },
  {
    "company": "Vertex Systems",
    "clientMatterNumber": "CM1017",
    "contactFirstName": "David",
    "contactLastName": "Anderson",
    "dlaFirstName": "Grace",
    "dlaLastName": "Turner",
    "dlaContactIdentity": "DLA017"
  },
  {
    "company": "Vertex System Solutions",
    "clientMatterNumber": "CM1018",
    "contactFirstName": "Dave",
    "contactLastName": "Anderson",
    "dlaFirstName": "Grace",
    "dlaLastName": "Turner",
    "dlaContactIdentity": "DLA018"
  },
  {
    "company": "Summit Global",
    "clientMatterNumber": "CM1019",
    "contactFirstName": "Jennifer",
    "contactLastName": "Thomas",
    "dlaFirstName": "Henry",
    "dlaLastName": "Lewis",
    "dlaContactIdentity": "DLA019"
  },
  {
    "company": "Summit Worldwide",
    "clientMatterNumber": "CM1020",
    "contactFirstName": "Jen",
    "contactLastName": "Thompson",
    "dlaFirstName": "Henry",
    "dlaLastName": "Lewis",
    "dlaContactIdentity": "DLA020"
  },
  {
    "company": "Atlas Finance",
    "clientMatterNumber": "CM1021",
    "contactFirstName": "Charles",
    "contactLastName": "Martinez",
    "dlaFirstName": "Olivia",
    "dlaLastName": "Hernandez",
    "dlaContactIdentity": "DLA021"
  },
  {
    "company": "Atlas Financial",
    "clientMatterNumber": "CM1022",
    "contactFirstName": "Charlie",
    "contactLastName": "Martinez",
    "dlaFirstName": "Olivia",
    "dlaLastName": "Hernandez",
    "dlaContactIdentity": "DLA022"
  },
  {
    "company": "Nova Energy",
    "clientMatterNumber": "CM1023",
    "contactFirstName": "Patricia",
    "contactLastName": "Rodriguez",
    "dlaFirstName": "Lucas",
    "dlaLastName": "Allen",
    "dlaContactIdentity": "DLA023"
  },
  {
    "company": "Nova Energies",
    "clientMatterNumber": "CM1024",
    "contactFirstName": "Pat",
    "contactLastName": "Rodriguez",
    "dlaFirstName": "Lucas",
    "dlaLastName": "Allen",
    "dlaContactIdentity": "DLA024"
  },
  {
    "company": "Quantum Labs",
    "clientMatterNumber": "CM1025",
    "contactFirstName": "Christopher",
    "contactLastName": "Lopez",
    "dlaFirstName": "Zoe",
    "dlaLastName": "Wright",
    "dlaContactIdentity": "DLA025"
  },
  {
    "company": "Quantum Laboratories",
    "clientMatterNumber": "CM1026",
    "contactFirstName": "Chris",
    "contactLastName": "Lopez",
    "dlaFirstName": "Zoe",
    "dlaLastName": "Wright",
    "dlaContactIdentity": "DLA026"
  },
  {
    "company": "Solaris Tech",
    "clientMatterNumber": "CM1027",
    "contactFirstName": "Daniel",
    "contactLastName": "Harris",
    "dlaFirstName": "Amelia",
    "dlaLastName": "Torres",
    "dlaContactIdentity": "DLA027"
  },
  {
    "company": "Solaris Technologies",
    "clientMatterNumber": "CM1028",
    "contactFirstName": "Dan",
    "contactLastName": "Harris",
    "dlaFirstName": "Amelia",
    "dlaLastName": "Torres",
    "dlaContactIdentity": "DLA028"
  },
  {
    "company": "Orion Industries",
    "clientMatterNumber": "CM1029",
    "contactFirstName": "Matthew",
    "contactLastName": "Clark",
    "dlaFirstName": "Ethan",
    "dlaLastName": "Walker",
    "dlaContactIdentity": "DLA029"
  },
  {
    "company": "Orion Indust",
    "clientMatterNumber": "CM1030",
    "contactFirstName": "Matt",
    "contactLastName": "Clarke",
    "dlaFirstName": "Ethan",
    "dlaLastName": "Walker",
    "dlaContactIdentity": "DLA030"
  },
  {
    "company": "Phoenix Global",
    "clientMatterNumber": "CM1031",
    "contactFirstName": "Ashley",
    "contactLastName": "Lewis",
    "dlaFirstName": "Victoria",
    "dlaLastName": "Hill",
    "dlaContactIdentity": "DLA031"
  },
  {
    "company": "Phoenix Worldwide",
    "clientMatterNumber": "CM1032",
    "contactFirstName": "Ashleigh",
    "contactLastName": "Lewis",
    "dlaFirstName": "Victoria",
    "dlaLastName": "Hill",
    "dlaContactIdentity": "DLA032"
  },
  {
    "company": "Aurora Systems",
    "clientMatterNumber": "CM1033",
    "contactFirstName": "Joshua",
    "contactLastName": "Allen",
    "dlaFirstName": "Jack",
    "dlaLastName": "Baker",
    "dlaContactIdentity": "DLA033"
  },
  {
    "company": "Aurora Systemics",
    "clientMatterNumber": "CM1034",
    "contactFirstName": "Josh",
    "contactLastName": "Allen",
    "dlaFirstName": "Jack",
    "dlaLastName": "Baker",
    "dlaContactIdentity": "DLA034"
  },
  {
    "company": "Pioneer Legal",
    "clientMatterNumber": "CM1035",
    "contactFirstName": "Andrew",
    "contactLastName": "King",
    "dlaFirstName": "Ella",
    "dlaLastName": "Gonzalez",
    "dlaContactIdentity": "DLA035"
  },
  {
    "company": "Pioneer Law",
    "clientMatterNumber": "CM1036",
    "contactFirstName": "Andy",
    "contactLastName": "King",
    "dlaFirstName": "Ella",
    "dlaLastName": "Gonzalez",
    "dlaContactIdentity": "DLA036"
  },
  {
    "company": "Libra Consulting",
    "clientMatterNumber": "CM1037",
    "contactFirstName": "Donna",
    "contactLastName": "Perez",
    "dlaFirstName": "Aiden",
    "dlaLastName": "Nelson",
    "dlaContactIdentity": "DLA037"
  },
  {
    "company": "Libra Consultants",
    "clientMatterNumber": "CM1038",
    "contactFirstName": "Dawn",
    "contactLastName": "Perez",
    "dlaFirstName": "Aiden",
    "dlaLastName": "Nelson",
    "dlaContactIdentity": "DLA038"
  },
  {
    "company": "Apex Advisors",
    "clientMatterNumber": "CM1039",
    "contactFirstName": "Steven",
    "contactLastName": "Edwards",
    "dlaFirstName": "Mia",
    "dlaLastName": "Mitchell",
    "dlaContactIdentity": "DLA039"
  },
  {
    "company": "Apex Advisory",
    "clientMatterNumber": "CM1040",
    "contactFirstName": "Steve",
    "contactLastName": "Edwardson",
    "dlaFirstName": "Mia",
    "dlaLastName": "Mitchell",
    "dlaContactIdentity": "DLA040"
  },
  {
    "company": "Horizon Ventures",
    "clientMatterNumber": "CM1041",
    "contactFirstName": "Karen",
    "contactLastName": "Collins",
    "dlaFirstName": "Noah",
    "dlaLastName": "Carter",
    "dlaContactIdentity": "DLA041"
  },
  {
    "company": "Horizon Venture",
    "clientMatterNumber": "CM1042",
    "contactFirstName": "Kara",
    "contactLastName": "Collins",
    "dlaFirstName": "Noah",
    "dlaLastName": "Carter",
    "dlaContactIdentity": "DLA042"
  },
  {
    "company": "Everest Group",
    "clientMatterNumber": "CM1043",
    "contactFirstName": "Brian",
    "contactLastName": "Stewart",
    "dlaFirstName": "Lily",
    "dlaLastName": "Phillips",
    "dlaContactIdentity": "DLA043"
  },
  {
    "company": "Everest Global",
    "clientMatterNumber": "CM1044",
    "contactFirstName": "Bryan",
    "contactLastName": "Stewart",
    "dlaFirstName": "Lily",
    "dlaLastName": "Phillips",
    "dlaContactIdentity": "DLA044"
  },
  {
    "company": "Zenith Capital",
    "clientMatterNumber": "CM1045",
    "contactFirstName": "Kevin",
    "contactLastName": "Sanchez",
    "dlaFirstName": "James",
    "dlaLastName": "Parker",
    "dlaContactIdentity": "DLA045"
  },
  {
    "company": "Zenith Capital Partners",
    "clientMatterNumber": "CM1046",
    "contactFirstName": "Kev",
    "contactLastName": "Sanchez",
    "dlaFirstName": "James",
    "dlaLastName": "Parker",
    "dlaContactIdentity": "DLA046"
  },
  {
    "company": "Nimbus Legal",
    "clientMatterNumber": "CM1047",
    "contactFirstName": "Angela",
    "contactLastName": "Roberts",
    "dlaFirstName": "Hannah",
    "dlaLastName": "Evans",
    "dlaContactIdentity": "DLA047"
  },
  {
    "company": "Nimbus Law",
    "clientMatterNumber": "CM1048",
    "contactFirstName": "Angie",
    "contactLastName": "Roberts",
    "dlaFirstName": "Hannah",
    "dlaLastName": "Evans",
    "dlaContactIdentity": "DLA048"
  },
  {
    "company": "Stratus Consulting",
    "clientMatterNumber": "CM1049",
    "contactFirstName": "George",
    "contactLastName": "Cook",
    "dlaFirstName": "Isabella",
    "dlaLastName": "Bryant",
    "dlaContactIdentity": "DLA049"
  },
  {
    "company": "Stratus Consultants",
    "clientMatterNumber": "CM1050",
    "contactFirstName": "Greg",
    "contactLastName": "Cooke",
    "dlaFirstName": "Isabella",
    "dlaLastName": "Bryant",
    "dlaContactIdentity": "DLA050"
  }
]
